# 类文件的结构

## 字节码指令简介

Java虚拟机的指令由**一个字节长度**的、代表着某种特定操作含义的数字（称为操作码，Opcode）以及跟随其后的零至多个代表此操作所需的参数（称为操作数，Operand）构成。

### 字节码与数据类型

部分特殊的字符来表明专门为哪种数据类型服务：i代表对int类型的数据操作，l代表long，s代表short，b代表byte，c代表char，f代表float，d代表double，a代表reference。

Java虚拟机指令集所支持的数据类型：

| opcode    | byte    | short   | int       | long    | float   | double  | char    | reference |
| --------- | ------- | ------- | --------- | ------- | ------- | ------- | ------- | --------- |
| Tipush    | bipush  | sipush  |
| Tconst    |         |         | iconst    | lconst  | fconst  | dconst  |         | aconst    |
| Tload     |         |         | iload     | lload   | fload   | dload   |         | aload     |
| Tstore    |         |         | istore    | lstore  | fstore  | dstore  |         | astore    |
| Tinc      |         |         | iinc      |
| Taload    | baload  | saload  | iaload    | laload  | faload  | daload  | caload  | aaload    |
| Tastore   | bastore | sastore | iastore   | lastore | fastore | dastore | castore | aastore   |
| Tadd      |         |         | iadd      | ladd    | fadd    | dadd    |
| Tsub      |         |         | isub      | lsub    | fsub    | dsub    |
| Tmul      |         |         | imul      | lmul    | fmul    | dmul    |
| Tdiv      |         |         | idiv      | ldiv    | fdiv    | ddiv    |
| Trem      |         |         | irem      | lrem    | frem    | drem    |
| Tneg      |         |         | ineg      | lneg    | fneg    | dneg    |
| Tshl      |         |         | ishl      | lshl    |
| Tshr      |         |         | ishr      | lshr    |
| Tushr     |         |         | iushr     | lushr   |
| Tand      |         |         | iand      | land    |
| Tor       |         |         | ior       | lor     |
| Txor      |         |         | ixor      | lxor    |
| i2T       | i2b     | i2s     |           | i21     | i2f     | i2d     |
| l2T       |         |         | l2i       |         | l2f     | l2d     |
| f2T       |         |         | f2i       | f21     |         | f2d     |
| d2T       |         |         | d2i       | d2l     | d2f     |
| Tcmp      |         |         |           | lcmp    |
| Tcmpl     |         |         |           |         | fcmpl   | dcmpl   |
| Tcmpg     |         |         |           |         | fcmpg   | dcmpg   |
| if_TcmpOP |         |         | if_icmpOP |         |         |         |         | if_acmpOP |
| Treturn   |         |         | ireturn   | lreturn | freturn | dreturn |         | areturn   |


编译器会在编译期或运行期将byte和short类型的数据带符号扩展（Sign-Extend）为相应的int类型数据，将boolean和char类型数据零位扩展（Zero-Extend）为相应的int类型数据。

### 加载和存储指令

加载和存储指令用于将数据在栈帧中的局部变量表和操作数栈之间来回传输

- 将一个局部变量加载到操作栈：`Tload`、`Tload_<n>`
- 将一个数值从操作数栈存储到局部变量表：`Tstore`、`Tstore_<n>`
- 将一个常量加载到操作数栈：`Tipush`、`ldc`、`ldc_w`、`ldc2_w`、`aconst_null`、`iconst_m1`、`iconst_<i>`、`lconst_<l>`、`fconst_<f>`、`dconst_<d>`
- 扩充局部变量表的访问索引的指令：wide

> `<>`中为操作数

存储数据的操作数栈和局部变量表主要由加载和存储指令进行操作，除此之外，还有少量指令，如访问对象的字段或数组元素的指令也会向操作数栈传输数据。

### 运算指令

算术指令用于对两个操作数栈上的值进行某种特定运算，并把结果重新存入到操作栈顶。

无论是哪种算术指令，均是使用Java虚拟机的**算术类型**来进行计算的。

- 加法指令：`Tadd`
- 减法指令：`Tsub`
- 乘法指令：`Tmul`
- 除法指令：`Tdiv`
- 求余指令：`Trem`
- 取反指令：`Tneg`
- 位移指令：`Tshl`、`Tshr`、`Tushr`
- 按位或指令：`Tor`
- 按位与指令：`Tand`
- 按位异或指令：`Txor`
- 局部变量自增指令：`Tinc`
- 比较指令：`Tcmpg`、`Tcmpl`、`Tcmp`

只有除法指令（`Tdiv`）以及求余指令（`Trem`）中当出现除数为零时会导致虚拟机抛出`ArithmeticException`异常，其余任何整型数运算场景都不应该抛出运行时异常。

> **IEEE 754规范**

### 类型转换指令

Java虚拟机直接支持（即转换时无须显式的转换指令）以下数值类型的宽化类型转换（Widening Numeric Conversion，即小范围类型向大范围类型的安全转换）与之相对的，处理窄化类型转换（Narrowing Numeric Conversion）时，就必须显式地使用转换指令来完成，这些转换指令包括`i2b`、`i2c`、`i2s`、`l2i`、`f2i`、`f2l`、`d2i`、`d2l`和`d2f`。窄化类型转换可能会导致转换结果**产生不同的正负号、不同的数量级的情况，转换过程很可能会导致数值的精度丢失**。

Java虚拟机将一个浮点值窄化转换为整数类型T（T限于int或long类型之一）的时候，必须遵循以下转换规则：

- 如果浮点值是NaN，那转换结果就是int或long类型的0。
- 如果浮点值不是无穷大的话，浮点值使用IEEE 754的向零舍入模式取整，获得整数值v。如果v在目标类型T（int或long）的表示范围之类，那转换结果就是v；否则，将根据v的符号，转换为T所能表示的最大或者最小正数。
  
从double类型到float类型做窄化转换的过程与IEEE 754中定义的一致，通过IEEE 754向最接近数舍入模式舍入得到一个可以使用float类型表示的数字。如果转换结果的绝对值太小、无法使用float来表示的话，将返回float类型的正负零；如果转换结果的绝对值太大、无法使用float来表示的话，将返回float类型的正负无穷大。对于double类型的NaN值将按规定转换为float类型的NaN值。

数值类型的窄化转换指令永远不可能导致虚拟机抛出运行时异常。

### 对象创建与访问指令

- 创建类实例的指令：`new`
- 创建数组的指令：`newarray`、`anewarray`、`multianewarray`
- 访问类字段（static字段，或者称为类变量）和实例字段（非static字段，或者称为实例变量）的指令：`getfield`、`putfield`、`getstatic`、`putstatic`
- 把一个数组元素加载到操作数栈的指令：`baload`、`caload`、`saload`、`iaload`、`laload`、`faload`、`daload`、`aaload`
- 将一个操作数栈的值储存到数组元素中的指令：`bastore`、`castore`、`sastore`、`iastore`、`fastore`、`dastore`、`aastore`
- 取数组长度的指令：`arraylength`
- 检查类实例类型的指令：`instanceof`、`checkcast`

### 操作数栈管理指令

直接操作操作数栈的指令

- 将操作数栈的栈顶一个或两个元素出栈：`pop`、`pop2`
- 复制栈顶一个或两个数值并将复制值或双份的复制值重新压入栈顶：`dup`、`dup2`、`dup_x1`、`dup2_x1`、`dup_x2`、`dup2_x2`
- 将栈最顶端的两个数值互换：`swap`

### 控制转移指令

控制转移指令可以让Java虚拟机有条件或无条件地从指定位置指令（而不是控制转移指令）的下一条指令继续执行程序，从概念模型上理解，可以认为控制指令就是在有条件或无条件地修改PC寄存器的值。

- 条件分支：`ifeq`、`iflt`、`ifle`、`ifne`、`ifgt`、`ifge`、`ifnull`、`ifnonnull`、`if_icmpeq`、`if_icmpne`、`if_icmplt`、`if_icmpgt`、`if_icmple`、`if_icmpge`、`if_acmpeq`和`if_acmpne`
- 复合条件分支：`tableswitch`、`lookupswitch`
- 无条件分支：`goto`、`goto_w`、`jsr`、`jsr_w`、`ret`

在Java虚拟机中有专门的指令集用来处理int和reference类型的条件分支比较操作，为了可以无须明显标识一个数据的值是否null，也有专门的指令用来检测null值。

与前面算术运算的规则一致，对于boolean类型、byte类型、char类型和short类型的条件分支比较操作，都使用int类型的比较指令来完成，而对于long类型、float类型和double类型的条件分支比较操作，则会先执行相应类型的比较运算指令（`dcmpg`、`dcmpl`、`fcmpg`、`fcmpl`、`lcmp`），运算指令会返回一个整型值到操作数栈中，随后再执行int类型的条件分支比较操作来完成整个分支跳转

### 方法调用和返回指令

- `invokevirtual`指令：用于调用对象的实例方法，根据对象的实际类型进行分派（虚方法分派），这也是Java语言中最常见的方法分派方式。
- `invokeinterface`指令：用于调用接口方法，它会在运行时搜索一个实现了这个接口方法的对象，找出适合的方法进行调用。
- `invokespecial`指令：用于调用一些需要特殊处理的实例方法，包括实例初始化方法、私有方法和父类方法。
- `invokestatic`指令：用于调用类静态方法（static方法）。
- `invokedynamic`指令：用于在运行时动态解析出调用点限定符所引用的方法。并执行该方法。前面四条调用指令的分派逻辑都固化在Java虚拟机内部，用户无法改变，而invokedynamic指令的分派逻辑是由用户所设定的引导方法决定的。

方法调用指令与数据类型无关，而方法返回指令是**根据返回值的类型区分**的，包括`ireturn`（当返回值是boolean、byte、char、short和int类型时使用）、`lreturn`、`freturn`、`dreturn`和`areturn`，另外还有一条return指令供声明为void的方法、实例初始化方法、类和接口的类初始化方法使用。

### 异常处理指令

在Java程序中显式抛出异常的操作（throw语句）都由`athrow`指令来实现。《Java虚拟机规范》还规定了许多运行时异常会在其他Java虚拟机指令检测到异常状况时自动抛出。

而在Java虚拟机中，处理异常（catch语句）不是由字节码指令来实现的，而是采用**异常表**来完成。

### 同步指令

Java虚拟机可以支持方法级的同步和方法内部一段指令序列的同步，这两种同步结构都是使用管程（Monitor，更常见的是直接将它称为“锁”）来实现的。

方法级的同步是隐式的，无须通过字节码指令来控制，它实现在方法调用和返回操作之中。虚拟机可以从**方法常量池中的方法表**结构中的`ACC_SYNCHRONIZED`访问标志得知一个方法是否被声明为同步方法。当方法调用时，调用指令将会检查方法的`ACC_SYNCHRONIZED`访问标志是否被设置，如果设置了，执行线程就要求先成功持有管程，然后才能执行方法，最后当方法完成（无论是正常完成还是非正常完成）时释放管程。在方法执行期间，执行线程持有了管程，其他任何线程都无法再获取到同一个管程。如果一个同步方法执行期间抛出了异常，并且在方法内部无法处理此异常，那这个同步方法**所持有的管程将在异常抛到同步方法边界之外时自动释放**。

同步一段指令集序列通常是由Java语言中的`synchronized`语句块来表示的，Java虚拟机的指令集中有`monitorenter`和`monitorexit`两条指令来支持synchronized关键字的语义，正确实现`synchronized`关键字**需要Javac编译器与Java虚拟机两者共同协作支持**。

eg:
```java
void onlyMe(Foo f) {
    synchronized(f) {
        doSomething();
    }
}
```

编译

```
Method void onlyMe(Foo)
0 aload_1                  // 将对象f入栈
1 dup                      // 复制栈顶元素（即f的引用）
2 astore_2                 // 将栈顶元素存储到局部变量表变量槽 2中
3 monitorenter             // 以栈定元素（即f）作为锁，开始同步
4 aload_0                  // 将局部变量槽 0（即this指针）的元素入栈
5 invokevirtual #5         // 调用doSomething()方法
8 aload_2                  // 将局部变量Slow 2的元素（即f）入栈
9 monitorexit              // 退出同步
10 goto 18                 // 方法正常结束，跳转到18返回
13 astore_3                // 从这步开始是异常路径，见下面异常表的Taget 13
14 aload_2                 // 将局部变量Slow 2的元素（即f）入栈
15 monitorexit             // 退出同步
16 aload_3                 // 将局部变量Slow 3的元素（即异常对象）入栈
17 athrow                  // 把异常对象重新抛出给onlyMe()方法的调用者
18 return                  // 方法正常返回
Exception table:
FromTo Target Type
     4     10   13  any
    13     16   13  any
```

编译器必须确保无论方法通过何种方式完成，方法中调用过的每条`monitorenter`指令都必须有其对应的`monitorexit`指令，而无论这个方法是正常结束还是异常结束。

为了保证在方法异常完成时`monitorenter`和`monitorexit`指令依然可以正确配对执行，编译器会**自动产生**一个异常处理程序，这个异常处理程序声明可处理所有的异常，它的**目的就是用来执行`monitorexit`指令**。

## 公有设计，私有实现

理解公有设计与私有实现之间的分界线是非常有必要的，任何一款Java虚拟机实现都必须能够读取Class文件并精确实现包含在其中的Java虚拟机代码的语义。

## Class文件结构的发展

Class文件格式所具备的平台中立（不依赖于特定硬件及操作系统）、紧凑、稳定和可扩展的特点，是Java技术体系实现平台无关、语言无关两项特性的重要支柱。